{
	"cmake" : 
	{
		"generator" : 
		{
			"multiConfig" : false,
			"name" : "Ninja"
		},
		"paths" : 
		{
			"cmake" : "/usr/bin/cmake",
			"cpack" : "/usr/bin/cpack",
			"ctest" : "/usr/bin/ctest",
			"root" : "/usr/share/cmake-4.0"
		},
		"version" : 
		{
			"isDirty" : false,
			"major" : 4,
			"minor" : 0,
			"patch" : 2,
			"string" : "4.0.2",
			"suffix" : ""
		}
	},
	"objects" : 
	[
		{
			"jsonFile" : "codemodel-v2-039cf662bd6e82434873.json",
			"kind" : "codemodel",
			"version" : 
			{
				"major" : 2,
				"minor" : 8
			}
		},
		{
			"jsonFile" : "cmakeFiles-v1-3da811ed19316a0249ee.json",
			"kind" : "cmakeFiles",
			"version" : 
			{
				"major" : 1,
				"minor" : 1
			}
		}
	],
	"reply" : 
	{
		"cmakeFiles-v1" : 
		{
			"jsonFile" : "cmakeFiles-v1-3da811ed19316a0249ee.json",
			"kind" : "cmakeFiles",
			"version" : 
			{
				"major" : 1,
				"minor" : 1
			}
		},
		"codemodel-v2" : 
		{
			"jsonFile" : "codemodel-v2-039cf662bd6e82434873.json",
			"kind" : "codemodel",
			"version" : 
			{
				"major" : 2,
				"minor" : 8
			}
		}
	}
}
